{"type":"PR","pr":{"number":12,"head":"5728afe08734e6f93df2a437c7cfc854a6bd416b"},"user":"jakubminka","branch":"cms/2019-02-22-šestý-příspěvek","collection":"prispevek","title":"Šestý příspěvek","description":"No Description!","objects":{"entry":{"path":"_posts/2019-02-22-šestý-příspěvek.md","sha":"c068852b6663d88793cf937226857579f1d9d2f5"},"files":[{"path":"/images/uploads/water-3021652_1920.jpg","sha":"e7a6dfb6fca2eac1a00e9cbaf5da0b57cc6b9815"}]},"timeStamp":"2019-03-06T19:53:12.492Z","status":"pending_publish"}